profile_fox
