Metadata-Version: 2.1
Name: profile-fox
Version: 1.0.3
Summary: Open things in a particular firefox profile from the command line
Home-page: https://github.com/talwrii/profile-fox
Author: readwithai
Author-email: talwrii@gmail.com
License: MIT
Keywords: firefox,tabs,profile
